<?xml version="1.0" encoding="utf-8"?>
<!DOCTYPE hibernate-mapping PUBLIC "-//Hibernate/Hibernate Mapping DTD 3.0//EN"
        "http://hibernate.sourceforge.net/hibernate-mapping-3.0.dtd">
<!-- 
    Mapping file autogenerated by MyEclipse Persistence Tools
-->
<hibernate-mapping>
    <class name="net.dqsy.papermg.sysmanager.po.PaperUserRole" table="paper_user_role" catalog="paper">
        <id name="userRoleId" type="integer">
            <column name="UserRoleId"/>
            <generator class="increment"/>
        </id>
        <property name="flag" type="integer">
            <column name="flag"/>
        </property>
        <many-to-one name="paperUser" class="net.dqsy.papermg.sysmanager.po.PaperUser">
            <column name="UserId" not-null="true"/>
        </many-to-one>
        <many-to-one name="paperRole" class="net.dqsy.papermg.sysmanager.po.PaperRole" lazy="false">
            <column name="RoleId" not-null="true"/>
        </many-to-one>
    </class>
</hibernate-mapping>
